groqshell/__init__.py
groqshell/mainrich.py
groqshell_cli-0.0.22.dist-info/METADATA
groqshell_cli-0.0.22.dist-info/WHEEL
groqshell_cli-0.0.22.dist-info/entry_points.txt
groqshell_cli-0.0.22.dist-info/top_level.txt
groqshell_cli-0.0.22.dist-info/RECORD
