Metadata-Version: 2.1
Name: groqshell_cli
Version: 0.0.22
Summary: Command-line interface for Groq AI models
Author: Revaz Goguadze
Author-email: <goguadze.rezi2022@gmail.com>
Keywords: python,groq,ai,cli,shell,interface
Classifier: Development Status :: 3 - Alpha
Classifier: Intended Audience :: Developers
Classifier: Programming Language :: Python :: 3
Classifier: Operating System :: Unix
Classifier: Operating System :: MacOS :: MacOS X
Classifier: Operating System :: Microsoft :: Windows
Requires-Dist: groq
Requires-Dist: colorama
Requires-Dist: rich
Requires-Dist: pygments
